pysru_accounting/__init__.py
pysru_accounting/blankettsru.py
pysru_accounting/infosru.py
pysru_accounting-0.0.2.dist-info/licenses/LICENSE
pysru_accounting-0.0.2.dist-info/METADATA
pysru_accounting-0.0.2.dist-info/WHEEL
pysru_accounting-0.0.2.dist-info/top_level.txt
pysru_accounting-0.0.2.dist-info/RECORD
