Metadata-Version: 2.4
Name: pysru-accounting
Version: 0.0.2
Summary: SRU file encoder
Author-email: Thomas Petig <thomas@petig.eu>
Project-URL: Homepage, https://github.com/thpe/pysru-accounting
Classifier: Programming Language :: Python :: 3
Classifier: License :: OSI Approved :: MIT License
Classifier: Operating System :: OS Independent
License-File: LICENSE
Dynamic: license-file
